probable_fiesta/__about__.py
probable_fiesta/__init__.py
probable_fiesta/app/__init__.py
probable_fiesta/app/main.py
probable_fiesta/app/builder/__init__.py
probable_fiesta/app/builder/app_abstract_machine.py
probable_fiesta/app/builder/app_builder.py
probable_fiesta/app/builder/command_context_factory.py
probable_fiesta/app/builder/context.py
probable_fiesta/app/builder/context_builder.py
probable_fiesta/app/builder/context_factory.py
probable_fiesta/app/builder/context_holder.py
probable_fiesta/cli/__init__.py
probable_fiesta/cli/builder/my_args_parser.py
probable_fiesta/cli/builder/parser.py
probable_fiesta/cli/builder/parser_builder.py
probable_fiesta/cli/builder/parser_factory.py
probable_fiesta/command/__init__.py
probable_fiesta/command/builder/__init__.py
probable_fiesta/command/builder/command.py
probable_fiesta/command/builder/command_builder.py
probable_fiesta/command/builder/command_factory.py
probable_fiesta/command/builder/command_queue.py
probable_fiesta/command/builder/command_queue_factory.py
probable_fiesta/config/default_config.py
probable_fiesta/config/module_config.py
probable_fiesta/config/variables.py
probable_fiesta/config/builder/__init__.py
probable_fiesta/config/builder/config.py
probable_fiesta/config/builder/config_builder.py
probable_fiesta/config/builder/config_builder_factory.py
probable_fiesta/logger/README.md
probable_fiesta/logger/__init__.py
probable_fiesta/logger/logger_manager.py
probable_fiesta/logger/logging_config.py
probable_fiesta/logger/builder/__init__.py
probable_fiesta/logger/builder/logger.py
probable_fiesta/logger/builder/logger_factory.py
probable_fiesta/logger/builder/logger_machine.py
probable_fiesta/run/__init__.py
probable_fiesta/run/main.py
probable_fiesta-0.2.5.dist-info/METADATA
probable_fiesta-0.2.5.dist-info/WHEEL
probable_fiesta-0.2.5.dist-info/entry_points.txt
probable_fiesta-0.2.5.dist-info/licenses/LICENSE
probable_fiesta-0.2.5.dist-info/RECORD
