Metadata-Version: 2.1
Name: probable_fiesta
Version: 0.2.5
Summary: Python Core Package.
Project-URL: Homepage, https://github.com/sergio-munoz/probable_fiesta/
Project-URL: Bug Tracker, https://github.com/sergio-munoz/probable_fiesta/issues
Project-URL: Documentation, https://github.com/sergio-munoz/probable_fiesta#readme
Project-URL: Issues, https://github.com/sergio-munoz/probable_fiesta/issues
Project-URL: Source, https://github.com/sergio-munoz/probable_fiesta
Author-email: Sergio Munoz <sergio.munoz@pubnub.com>
License: BSD 3-Clause License
License-File: LICENSE
Classifier: License :: OSI Approved :: MIT License
Classifier: Operating System :: OS Independent
Classifier: Programming Language :: Python
Classifier: Programming Language :: Python :: 3.7
Classifier: Programming Language :: Python :: 3.8
Classifier: Programming Language :: Python :: 3.9
Classifier: Programming Language :: Python :: 3.10
Classifier: Programming Language :: Python :: 3.11
Classifier: Programming Language :: Python :: Implementation :: CPython
Requires-Python: >=3.7
Requires-Dist: python-dotenv
